morilint/__init__.py
morilint/main.py
morilint/domain/__init__.py
morilint/domain/constants/__init__.py
morilint/domain/constants/emojies.py
morilint/domain/constants/file_ext.py
morilint/domain/constants/required_keywords.py
morilint/domain/dto/__init__.py
morilint/domain/dto/lint_report.py
morilint/domain/exceptions/__init__.py
morilint/domain/exceptions/base.py
morilint/domain/exceptions/hearth_missing_exception.py
morilint/domain/exceptions/keyword_exception.py
morilint/domain/exceptions/length_exception.py
morilint/domain/interfaces/__init__.py
morilint/domain/interfaces/lint_config.py
morilint/domain/services/__init__.py
morilint/domain/services/mori_lint_service.py
morilint/domain/use_cases/__init__.py
morilint/domain/use_cases/base.py
morilint/domain/use_cases/validate_hearts_include.py
morilint/domain/use_cases/validate_length.py
morilint/domain/use_cases/validate_required_keywords.py
morilint/infrastructure/__init__.py
morilint/infrastructure/lint_config/__init__.py
morilint/infrastructure/lint_config/config.py
morilint/infrastructure/logger/__init__.py
morilint/infrastructure/logger/logger.py
morilint/presentation/__init__.py
morilint/presentation/api/__init__.py
morilint/presentation/api/base/__init__.py
morilint/presentation/api/base/mori_linter.py
morilint/presentation/api/file_linter/__init__.py
morilint/presentation/api/file_linter/mori_file_linter.py
morilint/presentation/responses/__init__.py
morilint/presentation/responses/lint_file_response.py
morilint/presentation/responses/lint_response.py
morilint/presentation/utils/__init__.py
morilint/presentation/utils/command_line_parser.py
morilint/typing/__init__.py
tests/__init__.py
tests/conftest.py
tests/msg_fixtures.py
tests/test_api/__init__.py
tests/test_api/test_mori_linter.py
tests/test_domain/__init__.py
tests/test_domain/test_dto/__init__.py
tests/test_domain/test_dto/test_lint_report_dto.py
tests/test_domain/test_usecases/__init__.py
morilint-0.1.10.dist-info/LICENSE
morilint-0.1.10.dist-info/METADATA
morilint-0.1.10.dist-info/WHEEL
morilint-0.1.10.dist-info/entry_points.txt
morilint-0.1.10.dist-info/top_level.txt
morilint-0.1.10.dist-info/RECORD
