Metadata-Version: 2.1
Name: morilint
Version: 0.1.10
Summary: Мощный, либеральный, классный - Проверит сообщения, скажет, что не так
Author-email: Alexander Seryakov <seryakov78116@gmail.com>
License: Apache License
Project-URL: Homepage, https://github.com/BRunners8/morilint
Project-URL: Bug Tracker, https://github.com/BRunners8/morilint/issues
Classifier: Programming Language :: Python :: 3.12
Classifier: Topic :: Software Development :: Libraries
Classifier: Typing :: Typed
Classifier: Intended Audience :: Developers
Classifier: License :: OSI Approved :: Apache Software License
Classifier: Operating System :: OS Independent
Requires-Python: >=3.12
License-File: LICENSE
Requires-Dist: rich <=13.9.3
Requires-Dist: exceptiongroup >=1.1.3 ; python_version < "3.12"
